[
  {
    "load_time":"2025-04-01",
    "source_desc":"SURVEY",
    "year":2025,
    "freq_desc":"MONTHLY",
    "reference_period_desc":"JAN",
    "begin_code":1,
    "week_ending":null,
    "agg_level_desc":"NATIONAL",
    "domain_desc":"TOTAL",
    "state_alpha":"US",
    "region_desc":null,
    "commodity_desc":"SOYBEANS",
    "util_practice_desc":"ALL UTILIZATION PRACTICES",
    "statisticcat_desc":"CRUSHED",
    "unit_desc":"TONS",
    "short_desc":"SOYBEANS - CRUSHED, MEASURED IN TONS",
    "domaincat_desc":"NOT SPECIFIED",
    "class_desc":"ALL CLASSES",
    "Value":6376635
  },
  {
    "load_time":"2025-05-01",
    "source_desc":"SURVEY",
    "year":2025,
    "freq_desc":"MONTHLY",
    "reference_period_desc":"FEB",
    "begin_code":2,
    "week_ending":null,
    "agg_level_desc":"NATIONAL",
    "domain_desc":"TOTAL",
    "state_alpha":"US",
    "region_desc":null,
    "commodity_desc":"SOYBEANS",
    "util_practice_desc":"ALL UTILIZATION PRACTICES",
    "statisticcat_desc":"CRUSHED",
    "unit_desc":"TONS",
    "short_desc":"SOYBEANS - CRUSHED, MEASURED IN TONS",
    "domaincat_desc":"NOT SPECIFIED",
    "class_desc":"ALL CLASSES",
    "Value":5687304
  },
  {
    "load_time":"2025-06-02",
    "source_desc":"SURVEY",
    "year":2025,
    "freq_desc":"MONTHLY",
    "reference_period_desc":"MAR",
    "begin_code":3,
    "week_ending":null,
    "agg_level_desc":"NATIONAL",
    "domain_desc":"TOTAL",
    "state_alpha":"US",
    "region_desc":null,
    "commodity_desc":"SOYBEANS",
    "util_practice_desc":"ALL UTILIZATION PRACTICES",
    "statisticcat_desc":"CRUSHED",
    "unit_desc":"TONS",
    "short_desc":"SOYBEANS - CRUSHED, MEASURED IN TONS",
    "domaincat_desc":"NOT SPECIFIED",
    "class_desc":"ALL CLASSES",
    "Value":6202642
  },
  {
    "load_time":"2025-07-01",
    "source_desc":"SURVEY",
    "year":2025,
    "freq_desc":"MONTHLY",
    "reference_period_desc":"APR",
    "begin_code":4,
    "week_ending":null,
    "agg_level_desc":"NATIONAL",
    "domain_desc":"TOTAL",
    "state_alpha":"US",
    "region_desc":null,
    "commodity_desc":"SOYBEANS",
    "util_practice_desc":"ALL UTILIZATION PRACTICES",
    "statisticcat_desc":"CRUSHED",
    "unit_desc":"TONS",
    "short_desc":"SOYBEANS - CRUSHED, MEASURED IN TONS",
    "domaincat_desc":"NOT SPECIFIED",
    "class_desc":"ALL CLASSES",
    "Value":6071540
  },
  {
    "load_time":"2025-07-01",
    "source_desc":"SURVEY",
    "year":2025,
    "freq_desc":"MONTHLY",
    "reference_period_desc":"MAY",
    "begin_code":5,
    "week_ending":null,
    "agg_level_desc":"NATIONAL",
    "domain_desc":"TOTAL",
    "state_alpha":"US",
    "region_desc":null,
    "commodity_desc":"SOYBEANS",
    "util_practice_desc":"ALL UTILIZATION PRACTICES",
    "statisticcat_desc":"CRUSHED",
    "unit_desc":"TONS",
    "short_desc":"SOYBEANS - CRUSHED, MEASURED IN TONS",
    "domaincat_desc":"NOT SPECIFIED",
    "class_desc":"ALL CLASSES",
    "Value":6111115
  },
  {
    "load_time":"2025-04-01",
    "source_desc":"SURVEY",
    "year":2025,
    "freq_desc":"MONTHLY",
    "reference_period_desc":"JAN",
    "begin_code":1,
    "week_ending":null,
    "agg_level_desc":"REGION : MULTI-STATE",
    "domain_desc":"TOTAL",
    "state_alpha":null,
    "region_desc":"ILLINOIS",
    "commodity_desc":"SOYBEANS",
    "util_practice_desc":"ALL UTILIZATION PRACTICES",
    "statisticcat_desc":"CRUSHED",
    "unit_desc":"TONS",
    "short_desc":"SOYBEANS - CRUSHED, MEASURED IN TONS",
    "domaincat_desc":"NOT SPECIFIED",
    "class_desc":"ALL CLASSES",
    "Value":582101
  },
  {
    "load_time":"2025-05-01",
    "source_desc":"SURVEY",
    "year":2025,
    "freq_desc":"MONTHLY",
    "reference_period_desc":"FEB",
    "begin_code":2,
    "week_ending":null,
    "agg_level_desc":"REGION : MULTI-STATE",
    "domain_desc":"TOTAL",
    "state_alpha":null,
    "region_desc":"ILLINOIS",
    "commodity_desc":"SOYBEANS",
    "util_practice_desc":"ALL UTILIZATION PRACTICES",
    "statisticcat_desc":"CRUSHED",
    "unit_desc":"TONS",
    "short_desc":"SOYBEANS - CRUSHED, MEASURED IN TONS",
    "domaincat_desc":"NOT SPECIFIED",
    "class_desc":"ALL CLASSES",
    "Value":512114
  },
  {
    "load_time":"2025-06-02",
    "source_desc":"SURVEY",
    "year":2025,
    "freq_desc":"MONTHLY",
    "reference_period_desc":"MAR",
    "begin_code":3,
    "week_ending":null,
    "agg_level_desc":"REGION : MULTI-STATE",
    "domain_desc":"TOTAL",
    "state_alpha":null,
    "region_desc":"ILLINOIS",
    "commodity_desc":"SOYBEANS",
    "util_practice_desc":"ALL UTILIZATION PRACTICES",
    "statisticcat_desc":"CRUSHED",
    "unit_desc":"TONS",
    "short_desc":"SOYBEANS - CRUSHED, MEASURED IN TONS",
    "domaincat_desc":"NOT SPECIFIED",
    "class_desc":"ALL CLASSES",
    "Value":607551
  },
  {
    "load_time":"2025-07-01",
    "source_desc":"SURVEY",
    "year":2025,
    "freq_desc":"MONTHLY",
    "reference_period_desc":"APR",
    "begin_code":4,
    "week_ending":null,
    "agg_level_desc":"REGION : MULTI-STATE",
    "domain_desc":"TOTAL",
    "state_alpha":null,
    "region_desc":"ILLINOIS",
    "commodity_desc":"SOYBEANS",
    "util_practice_desc":"ALL UTILIZATION PRACTICES",
    "statisticcat_desc":"CRUSHED",
    "unit_desc":"TONS",
    "short_desc":"SOYBEANS - CRUSHED, MEASURED IN TONS",
    "domaincat_desc":"NOT SPECIFIED",
    "class_desc":"ALL CLASSES",
    "Value":628927
  },
  {
    "load_time":"2025-07-01",
    "source_desc":"SURVEY",
    "year":2025,
    "freq_desc":"MONTHLY",
    "reference_period_desc":"MAY",
    "begin_code":5,
    "week_ending":null,
    "agg_level_desc":"REGION : MULTI-STATE",
    "domain_desc":"TOTAL",
    "state_alpha":null,
    "region_desc":"ILLINOIS",
    "commodity_desc":"SOYBEANS",
    "util_practice_desc":"ALL UTILIZATION PRACTICES",
    "statisticcat_desc":"CRUSHED",
    "unit_desc":"TONS",
    "short_desc":"SOYBEANS - CRUSHED, MEASURED IN TONS",
    "domaincat_desc":"NOT SPECIFIED",
    "class_desc":"ALL CLASSES",
    "Value":643549
  },
  {
    "load_time":"2025-04-01",
    "source_desc":"SURVEY",
    "year":2025,
    "freq_desc":"MONTHLY",
    "reference_period_desc":"JAN",
    "begin_code":1,
    "week_ending":null,
    "agg_level_desc":"REGION : MULTI-STATE",
    "domain_desc":"TOTAL",
    "state_alpha":null,
    "region_desc":"IOWA",
    "commodity_desc":"SOYBEANS",
    "util_practice_desc":"ALL UTILIZATION PRACTICES",
    "statisticcat_desc":"CRUSHED",
    "unit_desc":"TONS",
    "short_desc":"SOYBEANS - CRUSHED, MEASURED IN TONS",
    "domaincat_desc":"NOT SPECIFIED",
    "class_desc":"ALL CLASSES",
    "Value":1397968
  },
  {
    "load_time":"2025-05-01",
    "source_desc":"SURVEY",
    "year":2025,
    "freq_desc":"MONTHLY",
    "reference_period_desc":"FEB",
    "begin_code":2,
    "week_ending":null,
    "agg_level_desc":"REGION : MULTI-STATE",
    "domain_desc":"TOTAL",
    "state_alpha":null,
    "region_desc":"IOWA",
    "commodity_desc":"SOYBEANS",
    "util_practice_desc":"ALL UTILIZATION PRACTICES",
    "statisticcat_desc":"CRUSHED",
    "unit_desc":"TONS",
    "short_desc":"SOYBEANS - CRUSHED, MEASURED IN TONS",
    "domaincat_desc":"NOT SPECIFIED",
    "class_desc":"ALL CLASSES",
    "Value":1291777
  },
  {
    "load_time":"2025-06-02",
    "source_desc":"SURVEY",
    "year":2025,
    "freq_desc":"MONTHLY",
    "reference_period_desc":"MAR",
    "begin_code":3,
    "week_ending":null,
    "agg_level_desc":"REGION : MULTI-STATE",
    "domain_desc":"TOTAL",
    "state_alpha":null,
    "region_desc":"IOWA",
    "commodity_desc":"SOYBEANS",
    "util_practice_desc":"ALL UTILIZATION PRACTICES",
    "statisticcat_desc":"CRUSHED",
    "unit_desc":"TONS",
    "short_desc":"SOYBEANS - CRUSHED, MEASURED IN TONS",
    "domaincat_desc":"NOT SPECIFIED",
    "class_desc":"ALL CLASSES",
    "Value":1408926
  },
  {
    "load_time":"2025-07-01",
    "source_desc":"SURVEY",
    "year":2025,
    "freq_desc":"MONTHLY",
    "reference_period_desc":"APR",
    "begin_code":4,
    "week_ending":null,
    "agg_level_desc":"REGION : MULTI-STATE",
    "domain_desc":"TOTAL",
    "state_alpha":null,
    "region_desc":"IOWA",
    "commodity_desc":"SOYBEANS",
    "util_practice_desc":"ALL UTILIZATION PRACTICES",
    "statisticcat_desc":"CRUSHED",
    "unit_desc":"TONS",
    "short_desc":"SOYBEANS - CRUSHED, MEASURED IN TONS",
    "domaincat_desc":"NOT SPECIFIED",
    "class_desc":"ALL CLASSES",
    "Value":1331350
  },
  {
    "load_time":"2025-07-01",
    "source_desc":"SURVEY",
    "year":2025,
    "freq_desc":"MONTHLY",
    "reference_period_desc":"MAY",
    "begin_code":5,
    "week_ending":null,
    "agg_level_desc":"REGION : MULTI-STATE",
    "domain_desc":"TOTAL",
    "state_alpha":null,
    "region_desc":"IOWA",
    "commodity_desc":"SOYBEANS",
    "util_practice_desc":"ALL UTILIZATION PRACTICES",
    "statisticcat_desc":"CRUSHED",
    "unit_desc":"TONS",
    "short_desc":"SOYBEANS - CRUSHED, MEASURED IN TONS",
    "domaincat_desc":"NOT SPECIFIED",
    "class_desc":"ALL CLASSES",
    "Value":1303682
  },
  {
    "load_time":"2025-04-01",
    "source_desc":"SURVEY",
    "year":2025,
    "freq_desc":"MONTHLY",
    "reference_period_desc":"JAN",
    "begin_code":1,
    "week_ending":null,
    "agg_level_desc":"REGION : MULTI-STATE",
    "domain_desc":"TOTAL",
    "state_alpha":null,
    "region_desc":"NORTH & EAST",
    "commodity_desc":"SOYBEANS",
    "util_practice_desc":"ALL UTILIZATION PRACTICES",
    "statisticcat_desc":"CRUSHED",
    "unit_desc":"TONS",
    "short_desc":"SOYBEANS - CRUSHED, MEASURED IN TONS",
    "domaincat_desc":"NOT SPECIFIED",
    "class_desc":"ALL CLASSES",
    "Value":1412991
  },
  {
    "load_time":"2025-05-01",
    "source_desc":"SURVEY",
    "year":2025,
    "freq_desc":"MONTHLY",
    "reference_period_desc":"FEB",
    "begin_code":2,
    "week_ending":null,
    "agg_level_desc":"REGION : MULTI-STATE",
    "domain_desc":"TOTAL",
    "state_alpha":null,
    "region_desc":"NORTH & EAST",
    "commodity_desc":"SOYBEANS",
    "util_practice_desc":"ALL UTILIZATION PRACTICES",
    "statisticcat_desc":"CRUSHED",
    "unit_desc":"TONS",
    "short_desc":"SOYBEANS - CRUSHED, MEASURED IN TONS",
    "domaincat_desc":"NOT SPECIFIED",
    "class_desc":"ALL CLASSES",
    "Value":1272385
  },
  {
    "load_time":"2025-06-02",
    "source_desc":"SURVEY",
    "year":2025,
    "freq_desc":"MONTHLY",
    "reference_period_desc":"MAR",
    "begin_code":3,
    "week_ending":null,
    "agg_level_desc":"REGION : MULTI-STATE",
    "domain_desc":"TOTAL",
    "state_alpha":null,
    "region_desc":"NORTH & EAST",
    "commodity_desc":"SOYBEANS",
    "util_practice_desc":"ALL UTILIZATION PRACTICES",
    "statisticcat_desc":"CRUSHED",
    "unit_desc":"TONS",
    "short_desc":"SOYBEANS - CRUSHED, MEASURED IN TONS",
    "domaincat_desc":"NOT SPECIFIED",
    "class_desc":"ALL CLASSES",
    "Value":1333008
  },
  {
    "load_time":"2025-07-01",
    "source_desc":"SURVEY",
    "year":2025,
    "freq_desc":"MONTHLY",
    "reference_period_desc":"APR",
    "begin_code":4,
    "week_ending":null,
    "agg_level_desc":"REGION : MULTI-STATE",
    "domain_desc":"TOTAL",
    "state_alpha":null,
    "region_desc":"NORTH & EAST",
    "commodity_desc":"SOYBEANS",
    "util_practice_desc":"ALL UTILIZATION PRACTICES",
    "statisticcat_desc":"CRUSHED",
    "unit_desc":"TONS",
    "short_desc":"SOYBEANS - CRUSHED, MEASURED IN TONS",
    "domaincat_desc":"NOT SPECIFIED",
    "class_desc":"ALL CLASSES",
    "Value":1351860
  },
  {
    "load_time":"2025-07-01",
    "source_desc":"SURVEY",
    "year":2025,
    "freq_desc":"MONTHLY",
    "reference_period_desc":"MAY",
    "begin_code":5,
    "week_ending":null,
    "agg_level_desc":"REGION : MULTI-STATE",
    "domain_desc":"TOTAL",
    "state_alpha":null,
    "region_desc":"NORTH & EAST",
    "commodity_desc":"SOYBEANS",
    "util_practice_desc":"ALL UTILIZATION PRACTICES",
    "statisticcat_desc":"CRUSHED",
    "unit_desc":"TONS",
    "short_desc":"SOYBEANS - CRUSHED, MEASURED IN TONS",
    "domaincat_desc":"NOT SPECIFIED",
    "class_desc":"ALL CLASSES",
    "Value":1334313
  },
  {
    "load_time":"2025-04-01",
    "source_desc":"SURVEY",
    "year":2025,
    "freq_desc":"MONTHLY",
    "reference_period_desc":"JAN",
    "begin_code":1,
    "week_ending":null,
    "agg_level_desc":"REGION : MULTI-STATE",
    "domain_desc":"TOTAL",
    "state_alpha":null,
    "region_desc":"NORTH CENTRAL",
    "commodity_desc":"SOYBEANS",
    "util_practice_desc":"ALL UTILIZATION PRACTICES",
    "statisticcat_desc":"CRUSHED",
    "unit_desc":"TONS",
    "short_desc":"SOYBEANS - CRUSHED, MEASURED IN TONS",
    "domaincat_desc":"NOT SPECIFIED",
    "class_desc":"ALL CLASSES",
    "Value":1223495
  },
  {
    "load_time":"2025-05-01",
    "source_desc":"SURVEY",
    "year":2025,
    "freq_desc":"MONTHLY",
    "reference_period_desc":"FEB",
    "begin_code":2,
    "week_ending":null,
    "agg_level_desc":"REGION : MULTI-STATE",
    "domain_desc":"TOTAL",
    "state_alpha":null,
    "region_desc":"NORTH CENTRAL",
    "commodity_desc":"SOYBEANS",
    "util_practice_desc":"ALL UTILIZATION PRACTICES",
    "statisticcat_desc":"CRUSHED",
    "unit_desc":"TONS",
    "short_desc":"SOYBEANS - CRUSHED, MEASURED IN TONS",
    "domaincat_desc":"NOT SPECIFIED",
    "class_desc":"ALL CLASSES",
    "Value":1066893
  },
  {
    "load_time":"2025-06-02",
    "source_desc":"SURVEY",
    "year":2025,
    "freq_desc":"MONTHLY",
    "reference_period_desc":"MAR",
    "begin_code":3,
    "week_ending":null,
    "agg_level_desc":"REGION : MULTI-STATE",
    "domain_desc":"TOTAL",
    "state_alpha":null,
    "region_desc":"NORTH CENTRAL",
    "commodity_desc":"SOYBEANS",
    "util_practice_desc":"ALL UTILIZATION PRACTICES",
    "statisticcat_desc":"CRUSHED",
    "unit_desc":"TONS",
    "short_desc":"SOYBEANS - CRUSHED, MEASURED IN TONS",
    "domaincat_desc":"NOT SPECIFIED",
    "class_desc":"ALL CLASSES",
    "Value":1139676
  },
  {
    "load_time":"2025-07-01",
    "source_desc":"SURVEY",
    "year":2025,
    "freq_desc":"MONTHLY",
    "reference_period_desc":"APR",
    "begin_code":4,
    "week_ending":null,
    "agg_level_desc":"REGION : MULTI-STATE",
    "domain_desc":"TOTAL",
    "state_alpha":null,
    "region_desc":"NORTH CENTRAL",
    "commodity_desc":"SOYBEANS",
    "util_practice_desc":"ALL UTILIZATION PRACTICES",
    "statisticcat_desc":"CRUSHED",
    "unit_desc":"TONS",
    "short_desc":"SOYBEANS - CRUSHED, MEASURED IN TONS",
    "domaincat_desc":"NOT SPECIFIED",
    "class_desc":"ALL CLASSES",
    "Value":1041654
  },
  {
    "load_time":"2025-07-01",
    "source_desc":"SURVEY",
    "year":2025,
    "freq_desc":"MONTHLY",
    "reference_period_desc":"MAY",
    "begin_code":5,
    "week_ending":null,
    "agg_level_desc":"REGION : MULTI-STATE",
    "domain_desc":"TOTAL",
    "state_alpha":null,
    "region_desc":"NORTH CENTRAL",
    "commodity_desc":"SOYBEANS",
    "util_practice_desc":"ALL UTILIZATION PRACTICES",
    "statisticcat_desc":"CRUSHED",
    "unit_desc":"TONS",
    "short_desc":"SOYBEANS - CRUSHED, MEASURED IN TONS",
    "domaincat_desc":"NOT SPECIFIED",
    "class_desc":"ALL CLASSES",
    "Value":1138781
  },
  {
    "load_time":"2025-04-01",
    "source_desc":"SURVEY",
    "year":2025,
    "freq_desc":"MONTHLY",
    "reference_period_desc":"JAN",
    "begin_code":1,
    "week_ending":null,
    "agg_level_desc":"REGION : MULTI-STATE",
    "domain_desc":"TOTAL",
    "state_alpha":null,
    "region_desc":"SOUTH, WEST, PACIFIC",
    "commodity_desc":"SOYBEANS",
    "util_practice_desc":"ALL UTILIZATION PRACTICES",
    "statisticcat_desc":"CRUSHED",
    "unit_desc":"TONS",
    "short_desc":"SOYBEANS - CRUSHED, MEASURED IN TONS",
    "domaincat_desc":"NOT SPECIFIED",
    "class_desc":"ALL CLASSES",
    "Value":651976
  },
  {
    "load_time":"2025-05-01",
    "source_desc":"SURVEY",
    "year":2025,
    "freq_desc":"MONTHLY",
    "reference_period_desc":"FEB",
    "begin_code":2,
    "week_ending":null,
    "agg_level_desc":"REGION : MULTI-STATE",
    "domain_desc":"TOTAL",
    "state_alpha":null,
    "region_desc":"SOUTH, WEST, PACIFIC",
    "commodity_desc":"SOYBEANS",
    "util_practice_desc":"ALL UTILIZATION PRACTICES",
    "statisticcat_desc":"CRUSHED",
    "unit_desc":"TONS",
    "short_desc":"SOYBEANS - CRUSHED, MEASURED IN TONS",
    "domaincat_desc":"NOT SPECIFIED",
    "class_desc":"ALL CLASSES",
    "Value":541402
  },
  {
    "load_time":"2025-06-02",
    "source_desc":"SURVEY",
    "year":2025,
    "freq_desc":"MONTHLY",
    "reference_period_desc":"MAR",
    "begin_code":3,
    "week_ending":null,
    "agg_level_desc":"REGION : MULTI-STATE",
    "domain_desc":"TOTAL",
    "state_alpha":null,
    "region_desc":"SOUTH, WEST, PACIFIC",
    "commodity_desc":"SOYBEANS",
    "util_practice_desc":"ALL UTILIZATION PRACTICES",
    "statisticcat_desc":"CRUSHED",
    "unit_desc":"TONS",
    "short_desc":"SOYBEANS - CRUSHED, MEASURED IN TONS",
    "domaincat_desc":"NOT SPECIFIED",
    "class_desc":"ALL CLASSES",
    "Value":602147
  },
  {
    "load_time":"2025-07-01",
    "source_desc":"SURVEY",
    "year":2025,
    "freq_desc":"MONTHLY",
    "reference_period_desc":"APR",
    "begin_code":4,
    "week_ending":null,
    "agg_level_desc":"REGION : MULTI-STATE",
    "domain_desc":"TOTAL",
    "state_alpha":null,
    "region_desc":"SOUTH, WEST, PACIFIC",
    "commodity_desc":"SOYBEANS",
    "util_practice_desc":"ALL UTILIZATION PRACTICES",
    "statisticcat_desc":"CRUSHED",
    "unit_desc":"TONS",
    "short_desc":"SOYBEANS - CRUSHED, MEASURED IN TONS",
    "domaincat_desc":"NOT SPECIFIED",
    "class_desc":"ALL CLASSES",
    "Value":635744
  },
  {
    "load_time":"2025-07-01",
    "source_desc":"SURVEY",
    "year":2025,
    "freq_desc":"MONTHLY",
    "reference_period_desc":"MAY",
    "begin_code":5,
    "week_ending":null,
    "agg_level_desc":"REGION : MULTI-STATE",
    "domain_desc":"TOTAL",
    "state_alpha":null,
    "region_desc":"SOUTH, WEST, PACIFIC",
    "commodity_desc":"SOYBEANS",
    "util_practice_desc":"ALL UTILIZATION PRACTICES",
    "statisticcat_desc":"CRUSHED",
    "unit_desc":"TONS",
    "short_desc":"SOYBEANS - CRUSHED, MEASURED IN TONS",
    "domaincat_desc":"NOT SPECIFIED",
    "class_desc":"ALL CLASSES",
    "Value":551218
  },
  {
    "load_time":"2025-04-01",
    "source_desc":"SURVEY",
    "year":2025,
    "freq_desc":"MONTHLY",
    "reference_period_desc":"JAN",
    "begin_code":1,
    "week_ending":null,
    "agg_level_desc":"REGION : MULTI-STATE",
    "domain_desc":"TOTAL",
    "state_alpha":null,
    "region_desc":"WEST CENTRAL",
    "commodity_desc":"SOYBEANS",
    "util_practice_desc":"ALL UTILIZATION PRACTICES",
    "statisticcat_desc":"CRUSHED",
    "unit_desc":"TONS",
    "short_desc":"SOYBEANS - CRUSHED, MEASURED IN TONS",
    "domaincat_desc":"NOT SPECIFIED",
    "class_desc":"ALL CLASSES",
    "Value":1108104
  },
  {
    "load_time":"2025-05-01",
    "source_desc":"SURVEY",
    "year":2025,
    "freq_desc":"MONTHLY",
    "reference_period_desc":"FEB",
    "begin_code":2,
    "week_ending":null,
    "agg_level_desc":"REGION : MULTI-STATE",
    "domain_desc":"TOTAL",
    "state_alpha":null,
    "region_desc":"WEST CENTRAL",
    "commodity_desc":"SOYBEANS",
    "util_practice_desc":"ALL UTILIZATION PRACTICES",
    "statisticcat_desc":"CRUSHED",
    "unit_desc":"TONS",
    "short_desc":"SOYBEANS - CRUSHED, MEASURED IN TONS",
    "domaincat_desc":"NOT SPECIFIED",
    "class_desc":"ALL CLASSES",
    "Value":1002733
  },
  {
    "load_time":"2025-06-02",
    "source_desc":"SURVEY",
    "year":2025,
    "freq_desc":"MONTHLY",
    "reference_period_desc":"MAR",
    "begin_code":3,
    "week_ending":null,
    "agg_level_desc":"REGION : MULTI-STATE",
    "domain_desc":"TOTAL",
    "state_alpha":null,
    "region_desc":"WEST CENTRAL",
    "commodity_desc":"SOYBEANS",
    "util_practice_desc":"ALL UTILIZATION PRACTICES",
    "statisticcat_desc":"CRUSHED",
    "unit_desc":"TONS",
    "short_desc":"SOYBEANS - CRUSHED, MEASURED IN TONS",
    "domaincat_desc":"NOT SPECIFIED",
    "class_desc":"ALL CLASSES",
    "Value":1111334
  },
  {
    "load_time":"2025-07-01",
    "source_desc":"SURVEY",
    "year":2025,
    "freq_desc":"MONTHLY",
    "reference_period_desc":"APR",
    "begin_code":4,
    "week_ending":null,
    "agg_level_desc":"REGION : MULTI-STATE",
    "domain_desc":"TOTAL",
    "state_alpha":null,
    "region_desc":"WEST CENTRAL",
    "commodity_desc":"SOYBEANS",
    "util_practice_desc":"ALL UTILIZATION PRACTICES",
    "statisticcat_desc":"CRUSHED",
    "unit_desc":"TONS",
    "short_desc":"SOYBEANS - CRUSHED, MEASURED IN TONS",
    "domaincat_desc":"NOT SPECIFIED",
    "class_desc":"ALL CLASSES",
    "Value":1082005
  },
  {
    "load_time":"2025-07-01",
    "source_desc":"SURVEY",
    "year":2025,
    "freq_desc":"MONTHLY",
    "reference_period_desc":"MAY",
    "begin_code":5,
    "week_ending":null,
    "agg_level_desc":"REGION : MULTI-STATE",
    "domain_desc":"TOTAL",
    "state_alpha":null,
    "region_desc":"WEST CENTRAL",
    "commodity_desc":"SOYBEANS",
    "util_practice_desc":"ALL UTILIZATION PRACTICES",
    "statisticcat_desc":"CRUSHED",
    "unit_desc":"TONS",
    "short_desc":"SOYBEANS - CRUSHED, MEASURED IN TONS",
    "domaincat_desc":"NOT SPECIFIED",
    "class_desc":"ALL CLASSES",
    "Value":1139572
  }
]