[
  {
    "load_time":"2025-04-01",
    "source_desc":"SURVEY",
    "year":2025,
    "freq_desc":"MONTHLY",
    "reference_period_desc":"JAN",
    "begin_code":1,
    "week_ending":null,
    "agg_level_desc":"NATIONAL",
    "domain_desc":"TOTAL",
    "state_alpha":"US",
    "region_desc":null,
    "commodity_desc":"CORN",
    "util_practice_desc":"FOR BEVERAGE ALCOHOL",
    "statisticcat_desc":"USAGE",
    "unit_desc":"BU",
    "short_desc":"CORN, FOR BEVERAGE ALCOHOL - USAGE, MEASURED IN BU",
    "domaincat_desc":"NOT SPECIFIED",
    "class_desc":"ALL CLASSES",
    "Value":2847000,
    "usage":"FOR BEVERAGE ALCOHOL"
  },
  {
    "load_time":"2025-05-01",
    "source_desc":"SURVEY",
    "year":2025,
    "freq_desc":"MONTHLY",
    "reference_period_desc":"FEB",
    "begin_code":2,
    "week_ending":null,
    "agg_level_desc":"NATIONAL",
    "domain_desc":"TOTAL",
    "state_alpha":"US",
    "region_desc":null,
    "commodity_desc":"CORN",
    "util_practice_desc":"FOR BEVERAGE ALCOHOL",
    "statisticcat_desc":"USAGE",
    "unit_desc":"BU",
    "short_desc":"CORN, FOR BEVERAGE ALCOHOL - USAGE, MEASURED IN BU",
    "domaincat_desc":"NOT SPECIFIED",
    "class_desc":"ALL CLASSES",
    "Value":3036000,
    "usage":"FOR BEVERAGE ALCOHOL"
  },
  {
    "load_time":"2025-06-02",
    "source_desc":"SURVEY",
    "year":2025,
    "freq_desc":"MONTHLY",
    "reference_period_desc":"MAR",
    "begin_code":3,
    "week_ending":null,
    "agg_level_desc":"NATIONAL",
    "domain_desc":"TOTAL",
    "state_alpha":"US",
    "region_desc":null,
    "commodity_desc":"CORN",
    "util_practice_desc":"FOR BEVERAGE ALCOHOL",
    "statisticcat_desc":"USAGE",
    "unit_desc":"BU",
    "short_desc":"CORN, FOR BEVERAGE ALCOHOL - USAGE, MEASURED IN BU",
    "domaincat_desc":"NOT SPECIFIED",
    "class_desc":"ALL CLASSES",
    "Value":4208000,
    "usage":"FOR BEVERAGE ALCOHOL"
  },
  {
    "load_time":"2025-07-01",
    "source_desc":"SURVEY",
    "year":2025,
    "freq_desc":"MONTHLY",
    "reference_period_desc":"APR",
    "begin_code":4,
    "week_ending":null,
    "agg_level_desc":"NATIONAL",
    "domain_desc":"TOTAL",
    "state_alpha":"US",
    "region_desc":null,
    "commodity_desc":"CORN",
    "util_practice_desc":"FOR BEVERAGE ALCOHOL",
    "statisticcat_desc":"USAGE",
    "unit_desc":"BU",
    "short_desc":"CORN, FOR BEVERAGE ALCOHOL - USAGE, MEASURED IN BU",
    "domaincat_desc":"NOT SPECIFIED",
    "class_desc":"ALL CLASSES",
    "Value":2683000,
    "usage":"FOR BEVERAGE ALCOHOL"
  },
  {
    "load_time":"2025-07-01",
    "source_desc":"SURVEY",
    "year":2025,
    "freq_desc":"MONTHLY",
    "reference_period_desc":"MAY",
    "begin_code":5,
    "week_ending":null,
    "agg_level_desc":"NATIONAL",
    "domain_desc":"TOTAL",
    "state_alpha":"US",
    "region_desc":null,
    "commodity_desc":"CORN",
    "util_practice_desc":"FOR BEVERAGE ALCOHOL",
    "statisticcat_desc":"USAGE",
    "unit_desc":"BU",
    "short_desc":"CORN, FOR BEVERAGE ALCOHOL - USAGE, MEASURED IN BU",
    "domaincat_desc":"NOT SPECIFIED",
    "class_desc":"ALL CLASSES",
    "Value":3800000,
    "usage":"FOR BEVERAGE ALCOHOL"
  },
  {
    "load_time":"2025-04-01",
    "source_desc":"SURVEY",
    "year":2025,
    "freq_desc":"MONTHLY",
    "reference_period_desc":"JAN",
    "begin_code":1,
    "week_ending":null,
    "agg_level_desc":"NATIONAL",
    "domain_desc":"TYPE OF OPERATION",
    "state_alpha":"US",
    "region_desc":null,
    "commodity_desc":"CORN",
    "util_practice_desc":"FOR FUEL ALCOHOL",
    "statisticcat_desc":"USAGE",
    "unit_desc":"BU",
    "short_desc":"CORN, FOR FUEL ALCOHOL - USAGE, MEASURED IN BU",
    "domaincat_desc":"TYPE OF OPERATION: (DRY MILL PLANT)",
    "class_desc":"ALL CLASSES",
    "Value":428993000,
    "usage":"FOR FUEL ALCOHOL_DRY"
  },
  {
    "load_time":"2025-05-01",
    "source_desc":"SURVEY",
    "year":2025,
    "freq_desc":"MONTHLY",
    "reference_period_desc":"FEB",
    "begin_code":2,
    "week_ending":null,
    "agg_level_desc":"NATIONAL",
    "domain_desc":"TYPE OF OPERATION",
    "state_alpha":"US",
    "region_desc":null,
    "commodity_desc":"CORN",
    "util_practice_desc":"FOR FUEL ALCOHOL",
    "statisticcat_desc":"USAGE",
    "unit_desc":"BU",
    "short_desc":"CORN, FOR FUEL ALCOHOL - USAGE, MEASURED IN BU",
    "domaincat_desc":"TYPE OF OPERATION: (DRY MILL PLANT)",
    "class_desc":"ALL CLASSES",
    "Value":387540000,
    "usage":"FOR FUEL ALCOHOL_DRY"
  },
  {
    "load_time":"2025-06-02",
    "source_desc":"SURVEY",
    "year":2025,
    "freq_desc":"MONTHLY",
    "reference_period_desc":"MAR",
    "begin_code":3,
    "week_ending":null,
    "agg_level_desc":"NATIONAL",
    "domain_desc":"TYPE OF OPERATION",
    "state_alpha":"US",
    "region_desc":null,
    "commodity_desc":"CORN",
    "util_practice_desc":"FOR FUEL ALCOHOL",
    "statisticcat_desc":"USAGE",
    "unit_desc":"BU",
    "short_desc":"CORN, FOR FUEL ALCOHOL - USAGE, MEASURED IN BU",
    "domaincat_desc":"TYPE OF OPERATION: (DRY MILL PLANT)",
    "class_desc":"ALL CLASSES",
    "Value":414876000,
    "usage":"FOR FUEL ALCOHOL_DRY"
  },
  {
    "load_time":"2025-07-01",
    "source_desc":"SURVEY",
    "year":2025,
    "freq_desc":"MONTHLY",
    "reference_period_desc":"APR",
    "begin_code":4,
    "week_ending":null,
    "agg_level_desc":"NATIONAL",
    "domain_desc":"TYPE OF OPERATION",
    "state_alpha":"US",
    "region_desc":null,
    "commodity_desc":"CORN",
    "util_practice_desc":"FOR FUEL ALCOHOL",
    "statisticcat_desc":"USAGE",
    "unit_desc":"BU",
    "short_desc":"CORN, FOR FUEL ALCOHOL - USAGE, MEASURED IN BU",
    "domaincat_desc":"TYPE OF OPERATION: (DRY MILL PLANT)",
    "class_desc":"ALL CLASSES",
    "Value":387086000,
    "usage":"FOR FUEL ALCOHOL_DRY"
  },
  {
    "load_time":"2025-07-01",
    "source_desc":"SURVEY",
    "year":2025,
    "freq_desc":"MONTHLY",
    "reference_period_desc":"MAY",
    "begin_code":5,
    "week_ending":null,
    "agg_level_desc":"NATIONAL",
    "domain_desc":"TYPE OF OPERATION",
    "state_alpha":"US",
    "region_desc":null,
    "commodity_desc":"CORN",
    "util_practice_desc":"FOR FUEL ALCOHOL",
    "statisticcat_desc":"USAGE",
    "unit_desc":"BU",
    "short_desc":"CORN, FOR FUEL ALCOHOL - USAGE, MEASURED IN BU",
    "domaincat_desc":"TYPE OF OPERATION: (DRY MILL PLANT)",
    "class_desc":"ALL CLASSES",
    "Value":413408000,
    "usage":"FOR FUEL ALCOHOL_DRY"
  },
  {
    "load_time":"2025-04-01",
    "source_desc":"SURVEY",
    "year":2025,
    "freq_desc":"MONTHLY",
    "reference_period_desc":"JAN",
    "begin_code":1,
    "week_ending":null,
    "agg_level_desc":"NATIONAL",
    "domain_desc":"TYPE OF OPERATION",
    "state_alpha":"US",
    "region_desc":null,
    "commodity_desc":"CORN",
    "util_practice_desc":"FOR FUEL ALCOHOL",
    "statisticcat_desc":"USAGE",
    "unit_desc":"BU",
    "short_desc":"CORN, FOR FUEL ALCOHOL - USAGE, MEASURED IN BU",
    "domaincat_desc":"TYPE OF OPERATION: (WET MILL PLANT)",
    "class_desc":"ALL CLASSES",
    "Value":38934000,
    "usage":"FOR FUEL ALCOHOL_WET"
  },
  {
    "load_time":"2025-05-01",
    "source_desc":"SURVEY",
    "year":2025,
    "freq_desc":"MONTHLY",
    "reference_period_desc":"FEB",
    "begin_code":2,
    "week_ending":null,
    "agg_level_desc":"NATIONAL",
    "domain_desc":"TYPE OF OPERATION",
    "state_alpha":"US",
    "region_desc":null,
    "commodity_desc":"CORN",
    "util_practice_desc":"FOR FUEL ALCOHOL",
    "statisticcat_desc":"USAGE",
    "unit_desc":"BU",
    "short_desc":"CORN, FOR FUEL ALCOHOL - USAGE, MEASURED IN BU",
    "domaincat_desc":"TYPE OF OPERATION: (WET MILL PLANT)",
    "class_desc":"ALL CLASSES",
    "Value":34198000,
    "usage":"FOR FUEL ALCOHOL_WET"
  },
  {
    "load_time":"2025-06-02",
    "source_desc":"SURVEY",
    "year":2025,
    "freq_desc":"MONTHLY",
    "reference_period_desc":"MAR",
    "begin_code":3,
    "week_ending":null,
    "agg_level_desc":"NATIONAL",
    "domain_desc":"TYPE OF OPERATION",
    "state_alpha":"US",
    "region_desc":null,
    "commodity_desc":"CORN",
    "util_practice_desc":"FOR FUEL ALCOHOL",
    "statisticcat_desc":"USAGE",
    "unit_desc":"BU",
    "short_desc":"CORN, FOR FUEL ALCOHOL - USAGE, MEASURED IN BU",
    "domaincat_desc":"TYPE OF OPERATION: (WET MILL PLANT)",
    "class_desc":"ALL CLASSES",
    "Value":38012000,
    "usage":"FOR FUEL ALCOHOL_WET"
  },
  {
    "load_time":"2025-07-01",
    "source_desc":"SURVEY",
    "year":2025,
    "freq_desc":"MONTHLY",
    "reference_period_desc":"APR",
    "begin_code":4,
    "week_ending":null,
    "agg_level_desc":"NATIONAL",
    "domain_desc":"TYPE OF OPERATION",
    "state_alpha":"US",
    "region_desc":null,
    "commodity_desc":"CORN",
    "util_practice_desc":"FOR FUEL ALCOHOL",
    "statisticcat_desc":"USAGE",
    "unit_desc":"BU",
    "short_desc":"CORN, FOR FUEL ALCOHOL - USAGE, MEASURED IN BU",
    "domaincat_desc":"TYPE OF OPERATION: (WET MILL PLANT)",
    "class_desc":"ALL CLASSES",
    "Value":36162000,
    "usage":"FOR FUEL ALCOHOL_WET"
  },
  {
    "load_time":"2025-07-01",
    "source_desc":"SURVEY",
    "year":2025,
    "freq_desc":"MONTHLY",
    "reference_period_desc":"MAY",
    "begin_code":5,
    "week_ending":null,
    "agg_level_desc":"NATIONAL",
    "domain_desc":"TYPE OF OPERATION",
    "state_alpha":"US",
    "region_desc":null,
    "commodity_desc":"CORN",
    "util_practice_desc":"FOR FUEL ALCOHOL",
    "statisticcat_desc":"USAGE",
    "unit_desc":"BU",
    "short_desc":"CORN, FOR FUEL ALCOHOL - USAGE, MEASURED IN BU",
    "domaincat_desc":"TYPE OF OPERATION: (WET MILL PLANT)",
    "class_desc":"ALL CLASSES",
    "Value":36030000,
    "usage":"FOR FUEL ALCOHOL_WET"
  },
  {
    "load_time":"2025-04-01",
    "source_desc":"SURVEY",
    "year":2025,
    "freq_desc":"MONTHLY",
    "reference_period_desc":"JAN",
    "begin_code":1,
    "week_ending":null,
    "agg_level_desc":"NATIONAL",
    "domain_desc":"TOTAL",
    "state_alpha":"US",
    "region_desc":null,
    "commodity_desc":"CORN",
    "util_practice_desc":"FOR INDUSTRIAL ALCOHOL",
    "statisticcat_desc":"USAGE",
    "unit_desc":"BU",
    "short_desc":"CORN, FOR INDUSTRIAL ALCOHOL - USAGE, MEASURED IN BU",
    "domaincat_desc":"NOT SPECIFIED",
    "class_desc":"ALL CLASSES",
    "Value":6456000,
    "usage":"FOR INDUSTRIAL ALCOHOL"
  },
  {
    "load_time":"2025-05-01",
    "source_desc":"SURVEY",
    "year":2025,
    "freq_desc":"MONTHLY",
    "reference_period_desc":"FEB",
    "begin_code":2,
    "week_ending":null,
    "agg_level_desc":"NATIONAL",
    "domain_desc":"TOTAL",
    "state_alpha":"US",
    "region_desc":null,
    "commodity_desc":"CORN",
    "util_practice_desc":"FOR INDUSTRIAL ALCOHOL",
    "statisticcat_desc":"USAGE",
    "unit_desc":"BU",
    "short_desc":"CORN, FOR INDUSTRIAL ALCOHOL - USAGE, MEASURED IN BU",
    "domaincat_desc":"NOT SPECIFIED",
    "class_desc":"ALL CLASSES",
    "Value":6092000,
    "usage":"FOR INDUSTRIAL ALCOHOL"
  },
  {
    "load_time":"2025-06-02",
    "source_desc":"SURVEY",
    "year":2025,
    "freq_desc":"MONTHLY",
    "reference_period_desc":"MAR",
    "begin_code":3,
    "week_ending":null,
    "agg_level_desc":"NATIONAL",
    "domain_desc":"TOTAL",
    "state_alpha":"US",
    "region_desc":null,
    "commodity_desc":"CORN",
    "util_practice_desc":"FOR INDUSTRIAL ALCOHOL",
    "statisticcat_desc":"USAGE",
    "unit_desc":"BU",
    "short_desc":"CORN, FOR INDUSTRIAL ALCOHOL - USAGE, MEASURED IN BU",
    "domaincat_desc":"NOT SPECIFIED",
    "class_desc":"ALL CLASSES",
    "Value":6662000,
    "usage":"FOR INDUSTRIAL ALCOHOL"
  },
  {
    "load_time":"2025-07-01",
    "source_desc":"SURVEY",
    "year":2025,
    "freq_desc":"MONTHLY",
    "reference_period_desc":"APR",
    "begin_code":4,
    "week_ending":null,
    "agg_level_desc":"NATIONAL",
    "domain_desc":"TOTAL",
    "state_alpha":"US",
    "region_desc":null,
    "commodity_desc":"CORN",
    "util_practice_desc":"FOR INDUSTRIAL ALCOHOL",
    "statisticcat_desc":"USAGE",
    "unit_desc":"BU",
    "short_desc":"CORN, FOR INDUSTRIAL ALCOHOL - USAGE, MEASURED IN BU",
    "domaincat_desc":"NOT SPECIFIED",
    "class_desc":"ALL CLASSES",
    "Value":7851000,
    "usage":"FOR INDUSTRIAL ALCOHOL"
  },
  {
    "load_time":"2025-07-01",
    "source_desc":"SURVEY",
    "year":2025,
    "freq_desc":"MONTHLY",
    "reference_period_desc":"MAY",
    "begin_code":5,
    "week_ending":null,
    "agg_level_desc":"NATIONAL",
    "domain_desc":"TOTAL",
    "state_alpha":"US",
    "region_desc":null,
    "commodity_desc":"CORN",
    "util_practice_desc":"FOR INDUSTRIAL ALCOHOL",
    "statisticcat_desc":"USAGE",
    "unit_desc":"BU",
    "short_desc":"CORN, FOR INDUSTRIAL ALCOHOL - USAGE, MEASURED IN BU",
    "domaincat_desc":"NOT SPECIFIED",
    "class_desc":"ALL CLASSES",
    "Value":7796000,
    "usage":"FOR INDUSTRIAL ALCOHOL"
  },
  {
    "load_time":"2025-04-01",
    "source_desc":"SURVEY",
    "year":2025,
    "freq_desc":"MONTHLY",
    "reference_period_desc":"JAN",
    "begin_code":1,
    "week_ending":null,
    "agg_level_desc":"NATIONAL",
    "domain_desc":"TYPE OF OPERATION",
    "state_alpha":"US",
    "region_desc":null,
    "commodity_desc":"CORN",
    "util_practice_desc":"FOR OTHER PRODUCTS (EXCL ALCOHOL)",
    "statisticcat_desc":"USAGE",
    "unit_desc":"BU",
    "short_desc":"CORN, FOR OTHER PRODUCTS (EXCL ALCOHOL) - USAGE, MEASURED IN BU",
    "domaincat_desc":"TYPE OF OPERATION: (WET MILL PLANT)",
    "class_desc":"ALL CLASSES",
    "Value":36745000,
    "usage":"FOR OTHER PRODUCTS"
  },
  {
    "load_time":"2025-05-01",
    "source_desc":"SURVEY",
    "year":2025,
    "freq_desc":"MONTHLY",
    "reference_period_desc":"FEB",
    "begin_code":2,
    "week_ending":null,
    "agg_level_desc":"NATIONAL",
    "domain_desc":"TYPE OF OPERATION",
    "state_alpha":"US",
    "region_desc":null,
    "commodity_desc":"CORN",
    "util_practice_desc":"FOR OTHER PRODUCTS (EXCL ALCOHOL)",
    "statisticcat_desc":"USAGE",
    "unit_desc":"BU",
    "short_desc":"CORN, FOR OTHER PRODUCTS (EXCL ALCOHOL) - USAGE, MEASURED IN BU",
    "domaincat_desc":"TYPE OF OPERATION: (WET MILL PLANT)",
    "class_desc":"ALL CLASSES",
    "Value":34517000,
    "usage":"FOR OTHER PRODUCTS"
  },
  {
    "load_time":"2025-06-02",
    "source_desc":"SURVEY",
    "year":2025,
    "freq_desc":"MONTHLY",
    "reference_period_desc":"MAR",
    "begin_code":3,
    "week_ending":null,
    "agg_level_desc":"NATIONAL",
    "domain_desc":"TYPE OF OPERATION",
    "state_alpha":"US",
    "region_desc":null,
    "commodity_desc":"CORN",
    "util_practice_desc":"FOR OTHER PRODUCTS (EXCL ALCOHOL)",
    "statisticcat_desc":"USAGE",
    "unit_desc":"BU",
    "short_desc":"CORN, FOR OTHER PRODUCTS (EXCL ALCOHOL) - USAGE, MEASURED IN BU",
    "domaincat_desc":"TYPE OF OPERATION: (WET MILL PLANT)",
    "class_desc":"ALL CLASSES",
    "Value":39138000,
    "usage":"FOR OTHER PRODUCTS"
  },
  {
    "load_time":"2025-07-01",
    "source_desc":"SURVEY",
    "year":2025,
    "freq_desc":"MONTHLY",
    "reference_period_desc":"APR",
    "begin_code":4,
    "week_ending":null,
    "agg_level_desc":"NATIONAL",
    "domain_desc":"TYPE OF OPERATION",
    "state_alpha":"US",
    "region_desc":null,
    "commodity_desc":"CORN",
    "util_practice_desc":"FOR OTHER PRODUCTS (EXCL ALCOHOL)",
    "statisticcat_desc":"USAGE",
    "unit_desc":"BU",
    "short_desc":"CORN, FOR OTHER PRODUCTS (EXCL ALCOHOL) - USAGE, MEASURED IN BU",
    "domaincat_desc":"TYPE OF OPERATION: (WET MILL PLANT)",
    "class_desc":"ALL CLASSES",
    "Value":39310000,
    "usage":"FOR OTHER PRODUCTS"
  },
  {
    "load_time":"2025-07-01",
    "source_desc":"SURVEY",
    "year":2025,
    "freq_desc":"MONTHLY",
    "reference_period_desc":"MAY",
    "begin_code":5,
    "week_ending":null,
    "agg_level_desc":"NATIONAL",
    "domain_desc":"TYPE OF OPERATION",
    "state_alpha":"US",
    "region_desc":null,
    "commodity_desc":"CORN",
    "util_practice_desc":"FOR OTHER PRODUCTS (EXCL ALCOHOL)",
    "statisticcat_desc":"USAGE",
    "unit_desc":"BU",
    "short_desc":"CORN, FOR OTHER PRODUCTS (EXCL ALCOHOL) - USAGE, MEASURED IN BU",
    "domaincat_desc":"TYPE OF OPERATION: (WET MILL PLANT)",
    "class_desc":"ALL CLASSES",
    "Value":40438000,
    "usage":"FOR OTHER PRODUCTS"
  }
]